[
  {
    "id": "platform_admin_okatech",
    "label": "Platform Admin",
    "mode": "platform_admin",
    "app_id": "comms-admin-console",
    "tenant_id": "okatech",
    "network": "gov-net-1",
    "network_type": "government",
    "realm": "platform",
    "actor_id": "platform-admin",
    "desired_modules": { "icom": true, "iboite": true, "iasted": true, "icorrespondance": true },
    "permissions": ["manage_apps", "manage_networks", "manage_modules", "view_all_tenants"],
    "description": "Full platform access - can manage apps, networks, and modules"
  },
  {
    "id": "service_gov_app",
    "label": "Gov Service",
    "mode": "service",
    "app_id": "gov-app-1",
    "tenant_id": "ministry-1",
    "network": "gov-net-1",
    "network_type": "government",
    "realm": "government",
    "actor_id": null,
    "desired_modules": { "icom": true, "iboite": true, "iasted": true, "icorrespondance": true },
    "permissions": [],
    "description": "Government app service account - full module access"
  },
  {
    "id": "service_commercial_app",
    "label": "Biz Service",
    "mode": "service",
    "app_id": "client-portal",
    "tenant_id": "client-1",
    "network": "commercial-net-1",
    "network_type": "commercial",
    "realm": "business",
    "actor_id": null,
    "desired_modules": { "icom": true, "iboite": true, "iasted": true, "icorrespondance": false },
    "permissions": [],
    "description": "Commercial app service account - no iCorrespondance access"
  },
  {
    "id": "delegated_citizen",
    "label": "Citizen (Delegated)",
    "mode": "delegated",
    "app_id": "idn-client-app",
    "tenant_id": "client-1",
    "network": "commercial-net-1",
    "network_type": "commercial",
    "realm": "citizen",
    "actor_id": "citizen-001",
    "desired_modules": { "icom": true, "iboite": true, "iasted": true, "icorrespondance": false },
    "permissions": [],
    "description": "Citizen accessing via idn.ga-like client app"
  },
  {
    "id": "delegated_gov_agent",
    "label": "Gov Agent (Delegated)",
    "mode": "delegated",
    "app_id": "gov-app-1",
    "tenant_id": "ministry-1",
    "network": "gov-net-1",
    "network_type": "government",
    "realm": "government",
    "actor_id": "agent-007",
    "desired_modules": { "icom": true, "iboite": true, "iasted": true, "icorrespondance": true },
    "permissions": [],
    "description": "Government agent accessing via official gov app"
  }
]
